{
  "main": {
    "id": "2e9225e34664efd4",
    "type": "split",
    "children": [
      {
        "id": "0571c1c94d829fac",
        "type": "tabs",
        "children": [
          {
            "id": "47ef711f7e8c1d64",
            "type": "leaf",
            "state": {
              "type": "markdown",
              "state": {
                "file": "Hotools-blender/3.形态键工具.md",
                "mode": "source",
                "source": false
              },
              "icon": "lucide-file",
              "title": "3.形态键工具"
            }
          }
        ]
      }
    ],
    "direction": "vertical"
  },
  "left": {
    "id": "1243752a4df710bb",
    "type": "split",
    "children": [
      {
        "id": "8a4c81639dc8783e",
        "type": "tabs",
        "children": [
          {
            "id": "b77831b90dd9f87b",
            "type": "leaf",
            "state": {
              "type": "file-explorer",
              "state": {
                "sortOrder": "alphabetical",
                "autoReveal": false
              },
              "icon": "lucide-folder-closed",
              "title": "文件列表"
            }
          },
          {
            "id": "0829eb50dbb8a2b3",
            "type": "leaf",
            "state": {
              "type": "search",
              "state": {
                "query": "",
                "matchingCase": false,
                "explainSearch": false,
                "collapseAll": false,
                "extraContext": false,
                "sortOrder": "alphabetical"
              },
              "icon": "lucide-search",
              "title": "搜索"
            }
          },
          {
            "id": "436d75c49c949463",
            "type": "leaf",
            "state": {
              "type": "bookmarks",
              "state": {},
              "icon": "lucide-bookmark",
              "title": "书签"
            }
          }
        ]
      }
    ],
    "direction": "horizontal",
    "width": 300
  },
  "right": {
    "id": "ba1ec06a672fb227",
    "type": "split",
    "children": [
      {
        "id": "6cea78168fbf9ccd",
        "type": "tabs",
        "children": [
          {
            "id": "2aa5a4c073617928",
            "type": "leaf",
            "state": {
              "type": "backlink",
              "state": {
                "file": "Hotools-blender/5.骨骼工具.md",
                "collapseAll": false,
                "extraContext": false,
                "sortOrder": "alphabetical",
                "showSearch": false,
                "searchQuery": "",
                "backlinkCollapsed": false,
                "unlinkedCollapsed": true
              },
              "icon": "links-coming-in",
              "title": "5.骨骼工具 的反向链接列表"
            }
          },
          {
            "id": "5acb7020384970a8",
            "type": "leaf",
            "state": {
              "type": "outgoing-link",
              "state": {
                "file": "category-folder/Some note.md",
                "linksCollapsed": false,
                "unlinkedCollapsed": true
              },
              "icon": "links-going-out",
              "title": "Some note 的出链列表"
            }
          },
          {
            "id": "f850ba7e9e699bea",
            "type": "leaf",
            "state": {
              "type": "tag",
              "state": {
                "sortOrder": "frequency",
                "useHierarchy": true,
                "showSearch": false,
                "searchQuery": ""
              },
              "icon": "lucide-tags",
              "title": "标签"
            }
          },
          {
            "id": "2d9129bb8dcf7983",
            "type": "leaf",
            "state": {
              "type": "outline",
              "state": {
                "file": "Hotools-blender/3.形态键工具.md",
                "followCursor": false,
                "showSearch": false,
                "searchQuery": ""
              },
              "icon": "lucide-list",
              "title": "3.形态键工具 的大纲"
            }
          }
        ],
        "currentTab": 3
      }
    ],
    "direction": "horizontal",
    "width": 300
  },
  "left-ribbon": {
    "hiddenItems": {
      "switcher:打开快速切换": false,
      "graph:查看关系图谱": false,
      "canvas:新建白板": false,
      "daily-notes:打开/创建今天的日记": false,
      "templates:插入模板": false,
      "command-palette:打开命令面板": false,
      "obsidian-git:Open Git source control": false
    }
  },
  "active": "47ef711f7e8c1d64",
  "lastOpenFiles": [
    "Hotools-blender/6.UV工具.md",
    "Hotools-blender/3.形态键工具.md",
    "_img/Pasted image 20250725043734.png",
    "Hotools-blender/2.顶点组工具.md",
    "安装与配置/4.待解决bug清单.md",
    "安装与配置/1.支持.md",
    "安装与配置/2.blender插件安装.md",
    "安装与配置/3.插件的更新.md",
    "安装与配置/index.md",
    "Hotools-blender/1.顶点色工具.md",
    "Hotools-blender/5.骨骼工具.md",
    "Hotools-blender/7.exIcon.md",
    "index.md",
    "Hotools-unity/index.md",
    "_img/Pasted image 20250722181331.png",
    "_img/Pasted image 20250722180917.png",
    "_img/Pasted image 20250722175936.png",
    "Hotools-blender/9.检查.md",
    "_img/Pasted image 20250722040502.png",
    "_img/Pasted image 20250722040439.png",
    "Hotools-blender/10.其他.md",
    "_img/Pasted image 20250721032913.png",
    "_img/Pasted image 20250721032850.png",
    "_img/Pasted image 20250721032741.png",
    "_img/Pasted image 20250721032726.png",
    "Hotools-blender/8.导出.md",
    "Hotools-blender/4.映射改名工具.md",
    "Hotools-unity/1.导入约束.md",
    "Hotools-blender/index.md",
    "Hotools-blender/支持.md",
    "Hotools-blender/blender插件安装.md",
    "_img",
    "安装与配置/Some note.md",
    "Hotools-unity",
    "Hotools-blender",
    "安装与配置"
  ]
}